docspring/__init__.py
docspring/api_client.py
docspring/api_response.py
docspring/configuration.py
docspring/exceptions.py
docspring/py.typed
docspring/rest.py
docspring/api/__init__.py
docspring/api/client.py
docspring/models/__init__.py
docspring/models/add_fields_data.py
docspring/models/batch_generate_pdfs201_response.py
docspring/models/combine_pdfs_data.py
docspring/models/combined_submission.py
docspring/models/combined_submission_action.py
docspring/models/copy_template_options.py
docspring/models/create_combined_submission_response.py
docspring/models/create_custom_file_data.py
docspring/models/create_custom_file_response.py
docspring/models/create_folder_data.py
docspring/models/create_html_template.py
docspring/models/create_pdf_submission_data.py
docspring/models/create_pdf_template.py
docspring/models/create_submission_data_request_data.py
docspring/models/create_submission_data_request_event_request.py
docspring/models/create_submission_data_request_event_response.py
docspring/models/create_submission_data_request_response.py
docspring/models/create_submission_data_request_token_response.py
docspring/models/create_submission_response.py
docspring/models/custom_file.py
docspring/models/error_or_multiple_errors_response.py
docspring/models/error_response.py
docspring/models/folder.py
docspring/models/json_schema.py
docspring/models/list_submissions_response.py
docspring/models/move_folder_data.py
docspring/models/move_template_data.py
docspring/models/multiple_errors_response.py
docspring/models/publish_version_data.py
docspring/models/rename_folder_data.py
docspring/models/restore_version_data.py
docspring/models/submission.py
docspring/models/submission422_response.py
docspring/models/submission_action.py
docspring/models/submission_batch.py
docspring/models/submission_batch_data.py
docspring/models/submission_batch_with_submissions.py
docspring/models/submission_data_request.py
docspring/models/submission_data_request_event.py
docspring-3.0.0.dist-info/LICENSE
docspring-3.0.0.dist-info/METADATA
docspring-3.0.0.dist-info/WHEEL
docspring-3.0.0.dist-info/top_level.txt
docspring-3.0.0.dist-info/RECORD
