Metadata-Version: 2.1
Name: docspring
Version: 3.0.0
Summary: DocSpring API
Home-page: UNKNOWN
Author: OpenAPI Generator community
Author-email: team@openapitools.org
License: UNKNOWN
Keywords: OpenAPI,OpenAPI-Generator,DocSpring API
Platform: UNKNOWN
License-File: LICENSE
Requires-Dist: urllib3 (<3.0.0,>=2.1.0)
Requires-Dist: python-dateutil (>=2.8.2)
Requires-Dist: pydantic (>=2)
Requires-Dist: typing-extensions (>=4.7.1)
Requires-Dist: lazy-imports (<2,>=1)
